metafab_python/__init__.py
metafab_python/api_client.py
metafab_python/configuration.py
metafab_python/exceptions.py
metafab_python/model_utils.py
metafab_python/rest.py
metafab_python/api/__init__.py
metafab_python/api/contracts_api.py
metafab_python/api/currencies_api.py
metafab_python/api/ecosystems_api.py
metafab_python/api/games_api.py
metafab_python/api/items_api.py
metafab_python/api/lootboxes_api.py
metafab_python/api/players_api.py
metafab_python/api/shops_api.py
metafab_python/api/transactions_api.py
metafab_python/api/wallets_api.py
metafab_python/apis/__init__.py
metafab_python/model/__init__.py
metafab_python/model/approve_ecosystem_game_request.py
metafab_python/model/auth_game200_response.py
metafab_python/model/auth_game200_response_all_of.py
metafab_python/model/auth_player200_response.py
metafab_python/model/auth_player200_response_all_of.py
metafab_python/model/auth_profile200_response.py
metafab_python/model/batch_mint_collection_items_request.py
metafab_python/model/batch_transfer_collection_items_request.py
metafab_python/model/batch_transfer_currency_request.py
metafab_python/model/burn_collection_item_request.py
metafab_python/model/burn_currency_request.py
metafab_python/model/collection_item.py
metafab_python/model/collection_item_attributes_inner.py
metafab_python/model/collection_item_attributes_inner_value.py
metafab_python/model/collection_model.py
metafab_python/model/contract_model.py
metafab_python/model/create_collection200_response.py
metafab_python/model/create_collection200_response_all_of.py
metafab_python/model/create_collection200_response_all_of_contract.py
metafab_python/model/create_collection200_response_all_of_contract_all_of.py
metafab_python/model/create_collection_item_request.py
metafab_python/model/create_collection_item_request_attributes_inner.py
metafab_python/model/create_collection_request.py
metafab_python/model/create_contract_request.py
metafab_python/model/create_currency200_response.py
metafab_python-1.5.1.dist-info/METADATA
metafab_python-1.5.1.dist-info/WHEEL
metafab_python-1.5.1.dist-info/top_level.txt
metafab_python-1.5.1.dist-info/RECORD
