Metadata-Version: 2.1
Name: metafab-python
Version: 1.5.1
Summary: MetaFab API
Home-page: https://pypi.org/project/metafab-python/
Author: MetaFab Team
Author-email: metafabproject@gmail.com
Keywords: OpenAPI,OpenAPI-Generator,MetaFab API
Requires-Python: >=3.6
Requires-Dist: urllib3 (>=1.25.3)
Requires-Dist: python-dateutil
